lorenzcycletoolkit.py
src/__init__.py
src/analysis/__init__.py
src/analysis/boundary_terms.py
src/analysis/conversion_terms.py
src/analysis/energy_contents.py
src/analysis/generation_and_dissipation_terms.py
src/frameworks/__init__.py
src/frameworks/lec_fixed_framework.py
src/frameworks/lec_moving_framework.py
src/plots/__init__.py
src/plots/map_box_limits.py
src/plots/map_track.py
src/plots/plot_LEC.py
src/plots/plot_LPS.py
src/plots/plot_boxplot.py
src/plots/plot_hovmoller.py
src/plots/plot_periods.py
src/plots/timeseries_terms.py
src/plots/timeseries_zeta_and_Z.py
src/plots/utils.py
src/utils/__init__.py
src/utils/box_data.py
src/utils/calc_averages.py
src/utils/calc_budget_and_residual.py
src/utils/select_area.py
src/utils/thermodynamics.py
src/utils/tools.py
tests/__init__.py
tests/test_ERA5_fixed.py
tests/test_ERA5_track.py
tests/test_R2_fixed.py
tests/test_R2_track.py
tests/test_cdsapi.py
lorenzcycletoolkit-1.1.7.dist-info/LICENSE
lorenzcycletoolkit-1.1.7.dist-info/METADATA
lorenzcycletoolkit-1.1.7.dist-info/WHEEL
lorenzcycletoolkit-1.1.7.dist-info/entry_points.txt
lorenzcycletoolkit-1.1.7.dist-info/top_level.txt
lorenzcycletoolkit-1.1.7.dist-info/RECORD
