Metadata-Version: 2.1
Name: lorenzcycletoolkit
Version: 1.1.7
Summary: A toolkit for calculating the Lorenz Energy Cycle in atmospheric systems
Author-email: Danilo Couto de Souza <danilo.oceano@gmail.com>
Project-URL: Documentation, https://lorenzcycletoolkit.readthedocs.io/
Project-URL: Source, https://github.com/daniloceano/LorenzCycleToolkit
Project-URL: Tracker, https://github.com/daniloceano/LorenzCycleToolkit/issues
Classifier: Development Status :: 4 - Beta
Classifier: Intended Audience :: Science/Research
Classifier: Topic :: Scientific/Engineering :: Atmospheric Science
Classifier: Programming Language :: Python :: 3
Classifier: Programming Language :: Python :: 3.12
Classifier: Operating System :: OS Independent
Requires-Python: >=3.12
License-File: LICENSE
Requires-Dist: cartopy>=0.21.0
Requires-Dist: cdsapi>=0.5.1
Requires-Dist: matplotlib>=3.5.0
Requires-Dist: metpy>=1.3.0
Requires-Dist: netCDF4>=1.5.8
Requires-Dist: numpy>=1.22.0
Requires-Dist: pandas>=1.4.0
Requires-Dist: pint>=0.19
Requires-Dist: scipy>=1.8.0
Requires-Dist: xarray>=2022.3.0
